boltrp/__init__.py
boltrp/functional.py
BoltRP-0.0.1.dist-info/LICENSE
BoltRP-0.0.1.dist-info/METADATA
BoltRP-0.0.1.dist-info/WHEEL
BoltRP-0.0.1.dist-info/top_level.txt
BoltRP-0.0.1.dist-info/RECORD
